neynpy-0.1.1.dist-info/METADATA
neynpy-0.1.1.dist-info/WHEEL
neynpy-0.1.1.dist-info/RECORD
neynpy-0.1.1.dist-info/top_level.txt
neynpy-0.1.1.dist-info/LICENSE
neynpy/__init__.py
neynpy/impl.cpython-37m-powerpc64le-linux-gnu.so
neynpy/core/__init__.py
neynpy/core/route.py
neynpy/core/server.py
neynpy/utils/const.py
neynpy/utils/__init__.py
neynpy/utils/logging.py
neynpy/utils/ipv6.py
neynpy/utils/exceptions.py
neynpy/http/__init__.py
neynpy/http/response.py
neynpy/http/request.py
