Metadata-Version: 2.1
Name: neynpy
Version: 0.1.1
Summary: Fast and Lightweight Pyhthon HTTP Library
Home-page: https://github.com/Neyn/neynpy
Author: Shahriar Rezghi, Ahmad Zolfaghari
Author-email: shahriar25.ss@gmail.com, ah8ad3@gmail.com
License: BSD 3-clause "New" or "Revised" license
Keywords: webserver,http-server,neyn,neynpy
Platform: UNKNOWN
